batch_processor_custom/__init__.py
batch_processor_custom/batch_processor.py
batch_processor_custom-0.1.1.dist-info/LICENSE
batch_processor_custom-0.1.1.dist-info/METADATA
batch_processor_custom-0.1.1.dist-info/WHEEL
batch_processor_custom-0.1.1.dist-info/top_level.txt
batch_processor_custom-0.1.1.dist-info/RECORD
